[
  {
    "id": 723,
    "name": "Goretusk Liver",
    "quality": "Common",
    "itemClass": "Tradeskill",
    "itemSubclass": "Cooking",
    "level": 10,
    "requiredLevel": 0,
    "sellPrice": 15,
    "description": "",
    "icon": "https://render.worldofwarcraft.com/us/icons/56/inv_misc_organ_04.jpg",
    "wowhead": "https://www.wowhead.com/item=723",
    "category": "tradegoods"
  },
  {
    "id": 765,
    "name": "Silverleaf",
    "quality": "Common",
    "itemClass": "Tradeskill",
    "itemSubclass": "Herb",
    "level": 10,
    "requiredLevel": 0,
    "sellPrice": 10,
    "description": "",
    "icon": "https://render.worldofwarcraft.com/us/icons/56/inv_misc_herb_10.jpg",
    "wowhead": "https://www.wowhead.com/item=765",
    "category": "tradegoods"
  },
  {
    "id": 769,
    "name": "Chunk of Boar Meat",
    "quality": "Common",
    "itemClass": "Tradeskill",
    "itemSubclass": "Cooking",
    "level": 10,
    "requiredLevel": 0,
    "sellPrice": 3,
    "description": "",
    "icon": "https://render.worldofwarcraft.com/us/icons/56/inv_misc_food_14.jpg",
    "wowhead": "https://www.wowhead.com/item=769",
    "category": "tradegoods"
  },
  {
    "id": 774,
    "name": "Malachite",
    "quality": "Uncommon",
    "itemClass": "Tradeskill",
    "itemSubclass": "Jewelcrafting",
    "level": 10,
    "requiredLevel": 0,
    "sellPrice": 50,
    "description": "",
    "icon": "https://render.worldofwarcraft.com/us/icons/56/inv_misc_gem_emerald_03.jpg",
    "wowhead": "https://www.wowhead.com/item=774",
    "category": "tradegoods"
  },
  {
    "id": 783,
    "name": "Light Hide",
    "quality": "Common",
    "itemClass": "Tradeskill",
    "itemSubclass": "Leather",
    "level": 10,
    "requiredLevel": 0,
    "sellPrice": 50,
    "description": "",
    "icon": "https://render.worldofwarcraft.com/us/icons/56/inv_misc_pelt_wolf_ruin_02.jpg",
    "wowhead": "https://www.wowhead.com/item=783",
    "category": "tradegoods"
  },
  {
    "id": 785,
    "name": "Mageroyal",
    "quality": "Common",
    "itemClass": "Tradeskill",
    "itemSubclass": "Herb",
    "level": 10,
    "requiredLevel": 0,
    "sellPrice": 20,
    "description": "",
    "icon": "https://render.worldofwarcraft.com/us/icons/56/inv_jewelry_talisman_03.jpg",
    "wowhead": "https://www.wowhead.com/item=785",
    "category": "tradegoods"
  },
  {
    "id": 814,
    "name": "Flask of Oil",
    "quality": "Common",
    "itemClass": "Tradeskill",
    "itemSubclass": "Parts",
    "level": 10,
    "requiredLevel": 0,
    "sellPrice": 25,
    "description": "",
    "icon": "https://render.worldofwarcraft.com/us/icons/56/inv_drink_07.jpg",
    "wowhead": "https://www.wowhead.com/item=814",
    "category": "tradegoods"
  },
  {
    "id": 818,
    "name": "Tigerseye",
    "quality": "Uncommon",
    "itemClass": "Tradeskill",
    "itemSubclass": "Jewelcrafting",
    "level": 10,
    "requiredLevel": 0,
    "sellPrice": 100,
    "description": "",
    "icon": "https://render.worldofwarcraft.com/us/icons/56/inv_misc_gem_opal_03.jpg",
    "wowhead": "https://www.wowhead.com/item=818",
    "category": "tradegoods"
  },
  {
    "id": 1015,
    "name": "Lean Wolf Flank",
    "quality": "Common",
    "itemClass": "Tradeskill",
    "itemSubclass": "Cooking",
    "level": 10,
    "requiredLevel": 0,
    "sellPrice": 24,
    "description": "",
    "icon": "https://render.worldofwarcraft.com/us/icons/56/inv_misc_food_14.jpg",
    "wowhead": "https://www.wowhead.com/item=1015",
    "category": "tradegoods"
  },
  {
    "id": 1080,
    "name": "Tough Condor Meat",
    "quality": "Common",
    "itemClass": "Tradeskill",
    "itemSubclass": "Cooking",
    "level": 10,
    "requiredLevel": 0,
    "sellPrice": 78,
    "description": "",
    "icon": "https://render.worldofwarcraft.com/us/icons/56/inv_misc_organ_06.jpg",
    "wowhead": "https://www.wowhead.com/item=1080",
    "category": "tradegoods"
  },
  {
    "id": 1206,
    "name": "Moss Agate",
    "quality": "Uncommon",
    "itemClass": "Tradeskill",
    "itemSubclass": "Jewelcrafting",
    "level": 10,
    "requiredLevel": 0,
    "sellPrice": 400,
    "description": "",
    "icon": "https://render.worldofwarcraft.com/us/icons/56/inv_misc_gem_emerald_02.jpg",
    "wowhead": "https://www.wowhead.com/item=1206",
    "category": "tradegoods"
  },
  {
    "id": 1210,
    "name": "Shadowgem",
    "quality": "Uncommon",
    "itemClass": "Tradeskill",
    "itemSubclass": "Jewelcrafting",
    "level": 10,
    "requiredLevel": 0,
    "sellPrice": 250,
    "description": "",
    "icon": "https://render.worldofwarcraft.com/us/icons/56/inv_misc_gem_amethyst_01.jpg",
    "wowhead": "https://www.wowhead.com/item=1210",
    "category": "tradegoods"
  },
  {
    "id": 1288,
    "name": "Large Venom Sac",
    "quality": "Common",
    "itemClass": "Tradeskill",
    "itemSubclass": "Other",
    "level": 10,
    "requiredLevel": 0,
    "sellPrice": 185,
    "description": "",
    "icon": "https://render.worldofwarcraft.com/us/icons/56/inv_misc_organ_01.jpg",
    "wowhead": "https://www.wowhead.com/item=1288",
    "category": "tradegoods"
  },
  {
    "id": 1468,
    "name": "Murloc Fin",
    "quality": "Common",
    "itemClass": "Tradeskill",
    "itemSubclass": "Cooking",
    "level": 10,
    "requiredLevel": 0,
    "sellPrice": 28,
    "description": "",
    "icon": "https://render.worldofwarcraft.com/us/icons/56/inv_misc_monsterscales_02.jpg",
    "wowhead": "https://www.wowhead.com/item=1468",
    "category": "tradegoods"
  },
  {
    "id": 1475,
    "name": "Small Venom Sac",
    "quality": "Common",
    "itemClass": "Tradeskill",
    "itemSubclass": "Other",
    "level": 10,
    "requiredLevel": 0,
    "sellPrice": 82,
    "description": "",
    "icon": "https://render.worldofwarcraft.com/us/icons/56/inv_misc_organ_02.jpg",
    "wowhead": "https://www.wowhead.com/item=1475",
    "category": "tradegoods"
  },
  {
    "id": 1529,
    "name": "Jade",
    "quality": "Uncommon",
    "itemClass": "Tradeskill",
    "itemSubclass": "Jewelcrafting",
    "level": 10,
    "requiredLevel": 0,
    "sellPrice": 700,
    "description": "",
    "icon": "https://render.worldofwarcraft.com/us/icons/56/inv_misc_gem_stone_01.jpg",
    "wowhead": "https://www.wowhead.com/item=1529",
    "category": "tradegoods"
  },
  {
    "id": 1705,
    "name": "Lesser Moonstone",
    "quality": "Uncommon",
    "itemClass": "Tradeskill",
    "itemSubclass": "Jewelcrafting",
    "level": 10,
    "requiredLevel": 0,
    "sellPrice": 600,
    "description": "",
    "icon": "https://render.worldofwarcraft.com/us/icons/56/inv_misc_gem_crystal_01.jpg",
    "wowhead": "https://www.wowhead.com/item=1705",
    "category": "tradegoods"
  },
  {
    "id": 2251,
    "name": "Gooey Spider Leg",
    "quality": "Common",
    "itemClass": "Tradeskill",
    "itemSubclass": "Cooking",
    "level": 10,
    "requiredLevel": 0,
    "sellPrice": 12,
    "description": "",
    "icon": "https://render.worldofwarcraft.com/us/icons/56/inv_misc_monsterspidercarapace_01.jpg",
    "wowhead": "https://www.wowhead.com/item=2251",
    "category": "tradegoods"
  },
  {
    "id": 2318,
    "name": "Light Leather",
    "quality": "Common",
    "itemClass": "Tradeskill",
    "itemSubclass": "Leather",
    "level": 10,
    "requiredLevel": 0,
    "sellPrice": 15,
    "description": "",
    "icon": "https://render.worldofwarcraft.com/us/icons/56/inv_misc_leatherscrap_03.jpg",
    "wowhead": "https://www.wowhead.com/item=2318",
    "category": "tradegoods"
  },
  {
    "id": 2319,
    "name": "Medium Leather",
    "quality": "Common",
    "itemClass": "Tradeskill",
    "itemSubclass": "Leather",
    "level": 10,
    "requiredLevel": 0,
    "sellPrice": 50,
    "description": "",
    "icon": "https://render.worldofwarcraft.com/us/icons/56/inv_misc_leatherscrap_05.jpg",
    "wowhead": "https://www.wowhead.com/item=2319",
    "category": "tradegoods"
  },
  {
    "id": 2320,
    "name": "Coarse Thread",
    "quality": "Common",
    "itemClass": "Tradeskill",
    "itemSubclass": "Cloth",
    "level": 10,
    "requiredLevel": 0,
    "sellPrice": 2,
    "description": "",
    "icon": "https://render.worldofwarcraft.com/us/icons/56/inv_fabric_linen_03.jpg",
    "wowhead": "https://www.wowhead.com/item=2320",
    "category": "tradegoods"
  },
  {
    "id": 2321,
    "name": "Fine Thread",
    "quality": "Common",
    "itemClass": "Tradeskill",
    "itemSubclass": "Cloth",
    "level": 10,
    "requiredLevel": 0,
    "sellPrice": 25,
    "description": "",
    "icon": "https://render.worldofwarcraft.com/us/icons/56/inv_fabric_wool_02.jpg",
    "wowhead": "https://www.wowhead.com/item=2321",
    "category": "tradegoods"
  },
  {
    "id": 2324,
    "name": "Bleach",
    "quality": "Common",
    "itemClass": "Tradeskill",
    "itemSubclass": "Other",
    "level": 10,
    "requiredLevel": 0,
    "sellPrice": 6,
    "description": "",
    "icon": "https://render.worldofwarcraft.com/us/icons/56/inv_drink_12.jpg",
    "wowhead": "https://www.wowhead.com/item=2324",
    "category": "tradegoods"
  },
  {
    "id": 2325,
    "name": "Black Dye",
    "quality": "Common",
    "itemClass": "Tradeskill",
    "itemSubclass": "Other",
    "level": 10,
    "requiredLevel": 0,
    "sellPrice": 250,
    "description": "",
    "icon": "https://render.worldofwarcraft.com/us/icons/56/inv_potion_63.jpg",
    "wowhead": "https://www.wowhead.com/item=2325",
    "category": "tradegoods"
  },
  {
    "id": 2447,
    "name": "Peacebloom",
    "quality": "Common",
    "itemClass": "Tradeskill",
    "itemSubclass": "Herb",
    "level": 10,
    "requiredLevel": 0,
    "sellPrice": 10,
    "description": "",
    "icon": "https://render.worldofwarcraft.com/us/icons/56/inv_misc_flower_02.jpg",
    "wowhead": "https://www.wowhead.com/item=2447",
    "category": "tradegoods"
  },
  {
    "id": 2449,
    "name": "Earthroot",
    "quality": "Common",
    "itemClass": "Tradeskill",
    "itemSubclass": "Herb",
    "level": 10,
    "requiredLevel": 0,
    "sellPrice": 20,
    "description": "",
    "icon": "https://render.worldofwarcraft.com/us/icons/56/inv_misc_herb_07.jpg",
    "wowhead": "https://www.wowhead.com/item=2449",
    "category": "tradegoods"
  },
  {
    "id": 2450,
    "name": "Briarthorn",
    "quality": "Common",
    "itemClass": "Tradeskill",
    "itemSubclass": "Herb",
    "level": 10,
    "requiredLevel": 0,
    "sellPrice": 25,
    "description": "",
    "icon": "https://render.worldofwarcraft.com/us/icons/56/inv_misc_root_01.jpg",
    "wowhead": "https://www.wowhead.com/item=2450",
    "category": "tradegoods"
  },
  {
    "id": 2452,
    "name": "Swiftthistle",
    "quality": "Common",
    "itemClass": "Tradeskill",
    "itemSubclass": "Herb",
    "level": 10,
    "requiredLevel": 0,
    "sellPrice": 15,
    "description": "",
    "icon": "https://render.worldofwarcraft.com/us/icons/56/inv_misc_herb_04.jpg",
    "wowhead": "https://www.wowhead.com/item=2452",
    "category": "tradegoods"
  },
  {
    "id": 2453,
    "name": "Bruiseweed",
    "quality": "Common",
    "itemClass": "Tradeskill",
    "itemSubclass": "Herb",
    "level": 10,
    "requiredLevel": 0,
    "sellPrice": 25,
    "description": "",
    "icon": "https://render.worldofwarcraft.com/us/icons/56/inv_misc_herb_01.jpg",
    "wowhead": "https://www.wowhead.com/item=2453",
    "category": "tradegoods"
  },
  {
    "id": 2589,
    "name": "Linen Cloth",
    "quality": "Common",
    "itemClass": "Tradeskill",
    "itemSubclass": "Cloth",
    "level": 10,
    "requiredLevel": 0,
    "sellPrice": 13,
    "description": "",
    "icon": "https://render.worldofwarcraft.com/us/icons/56/inv_fabric_linen_01.jpg",
    "wowhead": "https://www.wowhead.com/item=2589",
    "category": "tradegoods"
  },
  {
    "id": 2592,
    "name": "Wool Cloth",
    "quality": "Common",
    "itemClass": "Tradeskill",
    "itemSubclass": "Cloth",
    "level": 10,
    "requiredLevel": 0,
    "sellPrice": 33,
    "description": "",
    "icon": "https://render.worldofwarcraft.com/us/icons/56/inv_fabric_wool_01.jpg",
    "wowhead": "https://www.wowhead.com/item=2592",
    "category": "tradegoods"
  },
  {
    "id": 2604,
    "name": "Red Dye",
    "quality": "Common",
    "itemClass": "Tradeskill",
    "itemSubclass": "Other",
    "level": 10,
    "requiredLevel": 0,
    "sellPrice": 12,
    "description": "",
    "icon": "https://render.worldofwarcraft.com/us/icons/56/inv_potion_11.jpg",
    "wowhead": "https://www.wowhead.com/item=2604",
    "category": "tradegoods"
  },
  {
    "id": 2605,
    "name": "Green Dye",
    "quality": "Common",
    "itemClass": "Tradeskill",
    "itemSubclass": "Other",
    "level": 10,
    "requiredLevel": 0,
    "sellPrice": 25,
    "description": "",
    "icon": "https://render.worldofwarcraft.com/us/icons/56/inv_potion_12.jpg",
    "wowhead": "https://www.wowhead.com/item=2605",
    "category": "tradegoods"
  },
  {
    "id": 2665,
    "name": "Stormwind Seasoning Herbs",
    "quality": "Common",
    "itemClass": "Tradeskill",
    "itemSubclass": "Cooking",
    "level": 1,
    "requiredLevel": 0,
    "sellPrice": 5,
    "description": "",
    "icon": "https://render.worldofwarcraft.com/us/icons/56/inv_misc_dust_02.jpg",
    "wowhead": "https://www.wowhead.com/item=2665",
    "category": "tradegoods"
  },
  {
    "id": 2672,
    "name": "Stringy Wolf Meat",
    "quality": "Common",
    "itemClass": "Tradeskill",
    "itemSubclass": "Cooking",
    "level": 10,
    "requiredLevel": 0,
    "sellPrice": 4,
    "description": "",
    "icon": "https://render.worldofwarcraft.com/us/icons/56/inv_misc_food_14.jpg",
    "wowhead": "https://www.wowhead.com/item=2672",
    "category": "tradegoods"
  },
  {
    "id": 2673,
    "name": "Coyote Meat",
    "quality": "Common",
    "itemClass": "Tradeskill",
    "itemSubclass": "Cooking",
    "level": 10,
    "requiredLevel": 0,
    "sellPrice": 10,
    "description": "",
    "icon": "https://render.worldofwarcraft.com/us/icons/56/inv_misc_food_69.jpg",
    "wowhead": "https://www.wowhead.com/item=2673",
    "category": "tradegoods"
  },
  {
    "id": 2674,
    "name": "Crawler Meat",
    "quality": "Common",
    "itemClass": "Tradeskill",
    "itemSubclass": "Cooking",
    "level": 10,
    "requiredLevel": 0,
    "sellPrice": 12,
    "description": "",
    "icon": "https://render.worldofwarcraft.com/us/icons/56/inv_misc_food_51.jpg",
    "wowhead": "https://www.wowhead.com/item=2674",
    "category": "tradegoods"
  },
  {
    "id": 2675,
    "name": "Crawler Claw",
    "quality": "Common",
    "itemClass": "Tradeskill",
    "itemSubclass": "Cooking",
    "level": 10,
    "requiredLevel": 0,
    "sellPrice": 11,
    "description": "",
    "icon": "https://render.worldofwarcraft.com/us/icons/56/inv_misc_birdbeck_02.jpg",
    "wowhead": "https://www.wowhead.com/item=2675",
    "category": "tradegoods"
  },
  {
    "id": 2677,
    "name": "Boar Ribs",
    "quality": "Common",
    "itemClass": "Tradeskill",
    "itemSubclass": "Cooking",
    "level": 10,
    "requiredLevel": 0,
    "sellPrice": 15,
    "description": "",
    "icon": "https://render.worldofwarcraft.com/us/icons/56/inv_misc_food_16.jpg",
    "wowhead": "https://www.wowhead.com/item=2677",
    "category": "tradegoods"
  },
  {
    "id": 2770,
    "name": "Copper Ore",
    "quality": "Common",
    "itemClass": "Tradeskill",
    "itemSubclass": "Metal & Stone",
    "level": 10,
    "requiredLevel": 0,
    "sellPrice": 5,
    "description": "",
    "icon": "https://render.worldofwarcraft.com/us/icons/56/inv_ore_copper_01.jpg",
    "wowhead": "https://www.wowhead.com/item=2770",
    "category": "tradegoods"
  },
  {
    "id": 2771,
    "name": "Tin Ore",
    "quality": "Common",
    "itemClass": "Tradeskill",
    "itemSubclass": "Metal & Stone",
    "level": 10,
    "requiredLevel": 0,
    "sellPrice": 25,
    "description": "",
    "icon": "https://render.worldofwarcraft.com/us/icons/56/inv_ore_tin_01.jpg",
    "wowhead": "https://www.wowhead.com/item=2771",
    "category": "tradegoods"
  },
  {
    "id": 2772,
    "name": "Iron Ore",
    "quality": "Common",
    "itemClass": "Tradeskill",
    "itemSubclass": "Metal & Stone",
    "level": 10,
    "requiredLevel": 0,
    "sellPrice": 150,
    "description": "",
    "icon": "https://render.worldofwarcraft.com/us/icons/56/inv_ore_iron_01.jpg",
    "wowhead": "https://www.wowhead.com/item=2772",
    "category": "tradegoods"
  },
  {
    "id": 2775,
    "name": "Silver Ore",
    "quality": "Uncommon",
    "itemClass": "Tradeskill",
    "itemSubclass": "Metal & Stone",
    "level": 10,
    "requiredLevel": 0,
    "sellPrice": 75,
    "description": "",
    "icon": "https://render.worldofwarcraft.com/us/icons/56/inv_stone_16.jpg",
    "wowhead": "https://www.wowhead.com/item=2775",
    "category": "tradegoods"
  },
  {
    "id": 2776,
    "name": "Gold Ore",
    "quality": "Uncommon",
    "itemClass": "Tradeskill",
    "itemSubclass": "Metal & Stone",
    "level": 10,
    "requiredLevel": 0,
    "sellPrice": 500,
    "description": "",
    "icon": "https://render.worldofwarcraft.com/us/icons/56/inv_ore_gold_01.jpg",
    "wowhead": "https://www.wowhead.com/item=2776",
    "category": "tradegoods"
  },
  {
    "id": 2835,
    "name": "Rough Stone",
    "quality": "Common",
    "itemClass": "Tradeskill",
    "itemSubclass": "Metal & Stone",
    "level": 10,
    "requiredLevel": 0,
    "sellPrice": 2,
    "description": "",
    "icon": "https://render.worldofwarcraft.com/us/icons/56/inv_stone_06.jpg",
    "wowhead": "https://www.wowhead.com/item=2835",
    "category": "tradegoods"
  },
  {
    "id": 2836,
    "name": "Coarse Stone",
    "quality": "Common",
    "itemClass": "Tradeskill",
    "itemSubclass": "Metal & Stone",
    "level": 10,
    "requiredLevel": 0,
    "sellPrice": 15,
    "description": "",
    "icon": "https://render.worldofwarcraft.com/us/icons/56/inv_stone_09.jpg",
    "wowhead": "https://www.wowhead.com/item=2836",
    "category": "tradegoods"
  },
  {
    "id": 2838,
    "name": "Heavy Stone",
    "quality": "Common",
    "itemClass": "Tradeskill",
    "itemSubclass": "Metal & Stone",
    "level": 10,
    "requiredLevel": 0,
    "sellPrice": 60,
    "description": "",
    "icon": "https://render.worldofwarcraft.com/us/icons/56/inv_stone_12.jpg",
    "wowhead": "https://www.wowhead.com/item=2838",
    "category": "tradegoods"
  },
  {
    "id": 2840,
    "name": "Copper Bar",
    "quality": "Common",
    "itemClass": "Tradeskill",
    "itemSubclass": "Metal & Stone",
    "level": 10,
    "requiredLevel": 0,
    "sellPrice": 10,
    "description": "",
    "icon": "https://render.worldofwarcraft.com/us/icons/56/inv_ingot_02.jpg",
    "wowhead": "https://www.wowhead.com/item=2840",
    "category": "tradegoods"
  },
  {
    "id": 2841,
    "name": "Bronze Bar",
    "quality": "Common",
    "itemClass": "Tradeskill",
    "itemSubclass": "Metal & Stone",
    "level": 10,
    "requiredLevel": 0,
    "sellPrice": 50,
    "description": "",
    "icon": "https://render.worldofwarcraft.com/us/icons/56/inv_ingot_bronze.jpg",
    "wowhead": "https://www.wowhead.com/item=2841",
    "category": "tradegoods"
  },
  {
    "id": 2842,
    "name": "Silver Bar",
    "quality": "Uncommon",
    "itemClass": "Tradeskill",
    "itemSubclass": "Metal & Stone",
    "level": 10,
    "requiredLevel": 0,
    "sellPrice": 100,
    "description": "",
    "icon": "https://render.worldofwarcraft.com/us/icons/56/inv_ingot_01.jpg",
    "wowhead": "https://www.wowhead.com/item=2842",
    "category": "tradegoods"
  },
  {
    "id": 2886,
    "name": "Crag Boar Rib",
    "quality": "Common",
    "itemClass": "Tradeskill",
    "itemSubclass": "Cooking",
    "level": 10,
    "requiredLevel": 0,
    "sellPrice": 5,
    "description": "",
    "icon": "https://render.worldofwarcraft.com/us/icons/56/inv_misc_food_16.jpg",
    "wowhead": "https://www.wowhead.com/item=2886",
    "category": "tradegoods"
  },
  {
    "id": 2924,
    "name": "Crocolisk Meat",
    "quality": "Common",
    "itemClass": "Tradeskill",
    "itemSubclass": "Cooking",
    "level": 10,
    "requiredLevel": 0,
    "sellPrice": 16,
    "description": "",
    "icon": "https://render.worldofwarcraft.com/us/icons/56/inv_misc_food_14.jpg",
    "wowhead": "https://www.wowhead.com/item=2924",
    "category": "tradegoods"
  },
  {
    "id": 2934,
    "name": "Ruined Leather Scraps",
    "quality": "Common",
    "itemClass": "Tradeskill",
    "itemSubclass": "Leather",
    "level": 10,
    "requiredLevel": 0,
    "sellPrice": 7,
    "description": "",
    "icon": "https://render.worldofwarcraft.com/us/icons/56/inv_misc_pelt_bear_ruin_05.jpg",
    "wowhead": "https://www.wowhead.com/item=2934",
    "category": "tradegoods"
  },
  {
    "id": 2996,
    "name": "Bolt of Linen Cloth",
    "quality": "Common",
    "itemClass": "Tradeskill",
    "itemSubclass": "Cloth",
    "level": 10,
    "requiredLevel": 0,
    "sellPrice": 40,
    "description": "",
    "icon": "https://render.worldofwarcraft.com/us/icons/56/inv_fabric_linen_02.jpg",
    "wowhead": "https://www.wowhead.com/item=2996",
    "category": "tradegoods"
  },
  {
    "id": 2997,
    "name": "Bolt of Woolen Cloth",
    "quality": "Common",
    "itemClass": "Tradeskill",
    "itemSubclass": "Cloth",
    "level": 10,
    "requiredLevel": 0,
    "sellPrice": 100,
    "description": "",
    "icon": "https://render.worldofwarcraft.com/us/icons/56/inv_fabric_wool_03.jpg",
    "wowhead": "https://www.wowhead.com/item=2997",
    "category": "tradegoods"
  },
  {
    "id": 3164,
    "name": "Discolored Worg Heart",
    "quality": "Common",
    "itemClass": "Tradeskill",
    "itemSubclass": "Other",
    "level": 10,
    "requiredLevel": 0,
    "sellPrice": 33,
    "description": "",
    "icon": "https://render.worldofwarcraft.com/us/icons/56/inv_misc_organ_02.jpg",
    "wowhead": "https://www.wowhead.com/item=3164",
    "category": "tradegoods"
  },
  {
    "id": 3173,
    "name": "Bear Meat",
    "quality": "Common",
    "itemClass": "Tradeskill",
    "itemSubclass": "Cooking",
    "level": 10,
    "requiredLevel": 0,
    "sellPrice": 15,
    "description": "",
    "icon": "https://render.worldofwarcraft.com/us/icons/56/inv_misc_food_71.jpg",
    "wowhead": "https://www.wowhead.com/item=3173",
    "category": "tradegoods"
  },
  {
    "id": 3182,
    "name": "Spider's Silk",
    "quality": "Common",
    "itemClass": "Tradeskill",
    "itemSubclass": "Cloth",
    "level": 10,
    "requiredLevel": 0,
    "sellPrice": 387,
    "description": "",
    "icon": "https://render.worldofwarcraft.com/us/icons/56/spell_nature_web.jpg",
    "wowhead": "https://www.wowhead.com/item=3182",
    "category": "tradegoods"
  },
  {
    "id": 3355,
    "name": "Wild Steelbloom",
    "quality": "Common",
    "itemClass": "Tradeskill",
    "itemSubclass": "Herb",
    "level": 10,
    "requiredLevel": 0,
    "sellPrice": 50,
    "description": "",
    "icon": "https://render.worldofwarcraft.com/us/icons/56/inv_misc_flower_01.jpg",
    "wowhead": "https://www.wowhead.com/item=3355",
    "category": "tradegoods"
  },
  {
    "id": 3356,
    "name": "Kingsblood",
    "quality": "Common",
    "itemClass": "Tradeskill",
    "itemSubclass": "Herb",
    "level": 10,
    "requiredLevel": 0,
    "sellPrice": 30,
    "description": "",
    "icon": "https://render.worldofwarcraft.com/us/icons/56/inv_misc_herb_03.jpg",
    "wowhead": "https://www.wowhead.com/item=3356",
    "category": "tradegoods"
  },
  {
    "id": 3357,
    "name": "Liferoot",
    "quality": "Common",
    "itemClass": "Tradeskill",
    "itemSubclass": "Herb",
    "level": 10,
    "requiredLevel": 0,
    "sellPrice": 75,
    "description": "",
    "icon": "https://render.worldofwarcraft.com/us/icons/56/inv_misc_root_02.jpg",
    "wowhead": "https://www.wowhead.com/item=3357",
    "category": "tradegoods"
  },
  {
    "id": 3358,
    "name": "Khadgar's Whisker",
    "quality": "Common",
    "itemClass": "Tradeskill",
    "itemSubclass": "Herb",
    "level": 10,
    "requiredLevel": 0,
    "sellPrice": 175,
    "description": "",
    "icon": "https://render.worldofwarcraft.com/us/icons/56/inv_misc_herb_08.jpg",
    "wowhead": "https://www.wowhead.com/item=3358",
    "category": "tradegoods"
  },
  {
    "id": 3369,
    "name": "Grave Moss",
    "quality": "Common",
    "itemClass": "Tradeskill",
    "itemSubclass": "Herb",
    "level": 10,
    "requiredLevel": 0,
    "sellPrice": 25,
    "description": "",
    "icon": "https://render.worldofwarcraft.com/us/icons/56/inv_misc_dust_02.jpg",
    "wowhead": "https://www.wowhead.com/item=3369",
    "category": "tradegoods"
  },
  {
    "id": 3371,
    "name": "Crystal Vial",
    "quality": "Common",
    "itemClass": "Tradeskill",
    "itemSubclass": "Other",
    "level": 10,
    "requiredLevel": 0,
    "sellPrice": 5,
    "description": "",
    "icon": "https://render.worldofwarcraft.com/us/icons/56/inv_alchemy_leadedvial.jpg",
    "wowhead": "https://www.wowhead.com/item=3371",
    "category": "tradegoods"
  },
  {
    "id": 3404,
    "name": "Buzzard Wing",
    "quality": "Common",
    "itemClass": "Tradeskill",
    "itemSubclass": "Cooking",
    "level": 10,
    "requiredLevel": 0,
    "sellPrice": 181,
    "description": "",
    "icon": "https://render.worldofwarcraft.com/us/icons/56/inv_misc_monsterscales_02.jpg",
    "wowhead": "https://www.wowhead.com/item=3404",
    "category": "tradegoods"
  },
  {
    "id": 3470,
    "name": "Rough Grinding Stone",
    "quality": "Common",
    "itemClass": "Tradeskill",
    "itemSubclass": "Metal & Stone",
    "level": 10,
    "requiredLevel": 0,
    "sellPrice": 5,
    "description": "",
    "icon": "https://render.worldofwarcraft.com/us/icons/56/inv_stone_grindingstone_01.jpg",
    "wowhead": "https://www.wowhead.com/item=3470",
    "category": "tradegoods"
  },
  {
    "id": 3478,
    "name": "Coarse Grinding Stone",
    "quality": "Common",
    "itemClass": "Tradeskill",
    "itemSubclass": "Metal & Stone",
    "level": 10,
    "requiredLevel": 0,
    "sellPrice": 10,
    "description": "",
    "icon": "https://render.worldofwarcraft.com/us/icons/56/inv_stone_grindingstone_02.jpg",
    "wowhead": "https://www.wowhead.com/item=3478",
    "category": "tradegoods"
  },
  {
    "id": 3486,
    "name": "Heavy Grinding Stone",
    "quality": "Common",
    "itemClass": "Tradeskill",
    "itemSubclass": "Metal & Stone",
    "level": 10,
    "requiredLevel": 0,
    "sellPrice": 100,
    "description": "",
    "icon": "https://render.worldofwarcraft.com/us/icons/56/inv_stone_grindingstone_03.jpg",
    "wowhead": "https://www.wowhead.com/item=3486",
    "category": "tradegoods"
  },
  {
    "id": 3575,
    "name": "Iron Bar",
    "quality": "Common",
    "itemClass": "Tradeskill",
    "itemSubclass": "Metal & Stone",
    "level": 10,
    "requiredLevel": 0,
    "sellPrice": 200,
    "description": "",
    "icon": "https://render.worldofwarcraft.com/us/icons/56/inv_ingot_iron.jpg",
    "wowhead": "https://www.wowhead.com/item=3575",
    "category": "tradegoods"
  },
  {
    "id": 3576,
    "name": "Tin Bar",
    "quality": "Common",
    "itemClass": "Tradeskill",
    "itemSubclass": "Metal & Stone",
    "level": 10,
    "requiredLevel": 0,
    "sellPrice": 35,
    "description": "",
    "icon": "https://render.worldofwarcraft.com/us/icons/56/inv_ingot_05.jpg",
    "wowhead": "https://www.wowhead.com/item=3576",
    "category": "tradegoods"
  },
  {
    "id": 3577,
    "name": "Gold Bar",
    "quality": "Uncommon",
    "itemClass": "Tradeskill",
    "itemSubclass": "Metal & Stone",
    "level": 10,
    "requiredLevel": 0,
    "sellPrice": 600,
    "description": "",
    "icon": "https://render.worldofwarcraft.com/us/icons/56/inv_ingot_03.jpg",
    "wowhead": "https://www.wowhead.com/item=3577",
    "category": "tradegoods"
  },
  {
    "id": 3667,
    "name": "Tender Crocolisk Meat",
    "quality": "Common",
    "itemClass": "Tradeskill",
    "itemSubclass": "Cooking",
    "level": 10,
    "requiredLevel": 0,
    "sellPrice": 25,
    "description": "",
    "icon": "https://render.worldofwarcraft.com/us/icons/56/inv_misc_food_14.jpg",
    "wowhead": "https://www.wowhead.com/item=3667",
    "category": "tradegoods"
  },
  {
    "id": 3685,
    "name": "Raptor Egg",
    "quality": "Common",
    "itemClass": "Tradeskill",
    "itemSubclass": "Cooking",
    "level": 10,
    "requiredLevel": 0,
    "sellPrice": 71,
    "description": "",
    "icon": "https://render.worldofwarcraft.com/us/icons/56/inv_egg_03.jpg",
    "wowhead": "https://www.wowhead.com/item=3685",
    "category": "tradegoods"
  },
  {
    "id": 3712,
    "name": "Turtle Meat",
    "quality": "Common",
    "itemClass": "Tradeskill",
    "itemSubclass": "Cooking",
    "level": 10,
    "requiredLevel": 0,
    "sellPrice": 87,
    "description": "",
    "icon": "https://render.worldofwarcraft.com/us/icons/56/inv_misc_food_70.jpg",
    "wowhead": "https://www.wowhead.com/item=3712",
    "category": "tradegoods"
  },
  {
    "id": 3730,
    "name": "Big Bear Meat",
    "quality": "Common",
    "itemClass": "Tradeskill",
    "itemSubclass": "Cooking",
    "level": 10,
    "requiredLevel": 0,
    "sellPrice": 45,
    "description": "",
    "icon": "https://render.worldofwarcraft.com/us/icons/56/inv_misc_food_14.jpg",
    "wowhead": "https://www.wowhead.com/item=3730",
    "category": "tradegoods"
  },
  {
    "id": 3731,
    "name": "Lion Meat",
    "quality": "Common",
    "itemClass": "Tradeskill",
    "itemSubclass": "Cooking",
    "level": 10,
    "requiredLevel": 0,
    "sellPrice": 55,
    "description": "",
    "icon": "https://render.worldofwarcraft.com/us/icons/56/inv_misc_food_71.jpg",
    "wowhead": "https://www.wowhead.com/item=3731",
    "category": "tradegoods"
  },
  {
    "id": 3818,
    "name": "Fadeleaf",
    "quality": "Common",
    "itemClass": "Tradeskill",
    "itemSubclass": "Herb",
    "level": 10,
    "requiredLevel": 0,
    "sellPrice": 125,
    "description": "",
    "icon": "https://render.worldofwarcraft.com/us/icons/56/inv_misc_herb_12.jpg",
    "wowhead": "https://www.wowhead.com/item=3818",
    "category": "tradegoods"
  },
  {
    "id": 3819,
    "name": "Dragon's Teeth",
    "quality": "Common",
    "itemClass": "Tradeskill",
    "itemSubclass": "Herb",
    "level": 10,
    "requiredLevel": 0,
    "sellPrice": 100,
    "description": "",
    "icon": "https://render.worldofwarcraft.com/us/icons/56/inv_misc_herb_dragonsteeth.jpg",
    "wowhead": "https://www.wowhead.com/item=3819",
    "category": "tradegoods"
  },
  {
    "id": 3820,
    "name": "Stranglekelp",
    "quality": "Common",
    "itemClass": "Tradeskill",
    "itemSubclass": "Herb",
    "level": 10,
    "requiredLevel": 0,
    "sellPrice": 100,
    "description": "",
    "icon": "https://render.worldofwarcraft.com/us/icons/56/inv_misc_herb_11.jpg",
    "wowhead": "https://www.wowhead.com/item=3820",
    "category": "tradegoods"
  },
  {
    "id": 3821,
    "name": "Goldthorn",
    "quality": "Common",
    "itemClass": "Tradeskill",
    "itemSubclass": "Herb",
    "level": 10,
    "requiredLevel": 0,
    "sellPrice": 150,
    "description": "",
    "icon": "https://render.worldofwarcraft.com/us/icons/56/inv_misc_herb_15.jpg",
    "wowhead": "https://www.wowhead.com/item=3821",
    "category": "tradegoods"
  },
  {
    "id": 3857,
    "name": "Coal",
    "quality": "Common",
    "itemClass": "Tradeskill",
    "itemSubclass": "Metal & Stone",
    "level": 10,
    "requiredLevel": 0,
    "sellPrice": 125,
    "description": "",
    "icon": "https://render.worldofwarcraft.com/us/icons/56/inv_ore_tin_01.jpg",
    "wowhead": "https://www.wowhead.com/item=3857",
    "category": "tradegoods"
  },
  {
    "id": 3858,
    "name": "Mithril Ore",
    "quality": "Common",
    "itemClass": "Tradeskill",
    "itemSubclass": "Metal & Stone",
    "level": 10,
    "requiredLevel": 0,
    "sellPrice": 250,
    "description": "",
    "icon": "https://render.worldofwarcraft.com/us/icons/56/inv_ore_mithril_02.jpg",
    "wowhead": "https://www.wowhead.com/item=3858",
    "category": "tradegoods"
  },
  {
    "id": 3859,
    "name": "Steel Bar",
    "quality": "Common",
    "itemClass": "Tradeskill",
    "itemSubclass": "Metal & Stone",
    "level": 10,
    "requiredLevel": 0,
    "sellPrice": 60,
    "description": "",
    "icon": "https://render.worldofwarcraft.com/us/icons/56/inv_ingot_steel.jpg",
    "wowhead": "https://www.wowhead.com/item=3859",
    "category": "tradegoods"
  },
  {
    "id": 3860,
    "name": "Mithril Bar",
    "quality": "Common",
    "itemClass": "Tradeskill",
    "itemSubclass": "Metal & Stone",
    "level": 10,
    "requiredLevel": 0,
    "sellPrice": 400,
    "description": "",
    "icon": "https://render.worldofwarcraft.com/us/icons/56/inv_ingot_06.jpg",
    "wowhead": "https://www.wowhead.com/item=3860",
    "category": "tradegoods"
  },
  {
    "id": 3864,
    "name": "Citrine",
    "quality": "Uncommon",
    "itemClass": "Tradeskill",
    "itemSubclass": "Jewelcrafting",
    "level": 10,
    "requiredLevel": 0,
    "sellPrice": 800,
    "description": "",
    "icon": "https://render.worldofwarcraft.com/us/icons/56/inv_misc_gem_opal_02.jpg",
    "wowhead": "https://www.wowhead.com/item=3864",
    "category": "tradegoods"
  },
  {
    "id": 4231,
    "name": "Cured Light Hide",
    "quality": "Common",
    "itemClass": "Tradeskill",
    "itemSubclass": "Leather",
    "level": 10,
    "requiredLevel": 0,
    "sellPrice": 110,
    "description": "",
    "icon": "https://render.worldofwarcraft.com/us/icons/56/inv_misc_pelt_wolf_01.jpg",
    "wowhead": "https://www.wowhead.com/item=4231",
    "category": "tradegoods"
  },
  {
    "id": 4232,
    "name": "Medium Hide",
    "quality": "Common",
    "itemClass": "Tradeskill",
    "itemSubclass": "Leather",
    "level": 10,
    "requiredLevel": 0,
    "sellPrice": 125,
    "description": "",
    "icon": "https://render.worldofwarcraft.com/us/icons/56/inv_misc_pelt_boar_ruin_02.jpg",
    "wowhead": "https://www.wowhead.com/item=4232",
    "category": "tradegoods"
  },
  {
    "id": 4233,
    "name": "Cured Medium Hide",
    "quality": "Common",
    "itemClass": "Tradeskill",
    "itemSubclass": "Leather",
    "level": 10,
    "requiredLevel": 0,
    "sellPrice": 200,
    "description": "",
    "icon": "https://render.worldofwarcraft.com/us/icons/56/inv_misc_pelt_bear_02.jpg",
    "wowhead": "https://www.wowhead.com/item=4233",
    "category": "tradegoods"
  },
  {
    "id": 4234,
    "name": "Heavy Leather",
    "quality": "Common",
    "itemClass": "Tradeskill",
    "itemSubclass": "Leather",
    "level": 10,
    "requiredLevel": 0,
    "sellPrice": 150,
    "description": "",
    "icon": "https://render.worldofwarcraft.com/us/icons/56/inv_misc_leatherscrap_07.jpg",
    "wowhead": "https://www.wowhead.com/item=4234",
    "category": "tradegoods"
  },
  {
    "id": 4235,
    "name": "Heavy Hide",
    "quality": "Common",
    "itemClass": "Tradeskill",
    "itemSubclass": "Leather",
    "level": 10,
    "requiredLevel": 0,
    "sellPrice": 200,
    "description": "",
    "icon": "https://render.worldofwarcraft.com/us/icons/56/inv_misc_pelt_wolf_ruin_03.jpg",
    "wowhead": "https://www.wowhead.com/item=4235",
    "category": "tradegoods"
  },
  {
    "id": 4236,
    "name": "Cured Heavy Hide",
    "quality": "Common",
    "itemClass": "Tradeskill",
    "itemSubclass": "Leather",
    "level": 10,
    "requiredLevel": 0,
    "sellPrice": 225,
    "description": "",
    "icon": "https://render.worldofwarcraft.com/us/icons/56/inv_misc_pelt_wolf_02.jpg",
    "wowhead": "https://www.wowhead.com/item=4236",
    "category": "tradegoods"
  },
  {
    "id": 4289,
    "name": "Salt",
    "quality": "Common",
    "itemClass": "Tradeskill",
    "itemSubclass": "Leather",
    "level": 10,
    "requiredLevel": 0,
    "sellPrice": 12,
    "description": "",
    "icon": "https://render.worldofwarcraft.com/us/icons/56/inv_misc_dust_02.jpg",
    "wowhead": "https://www.wowhead.com/item=4289",
    "category": "tradegoods"
  },
  {
    "id": 4291,
    "name": "Silken Thread",
    "quality": "Common",
    "itemClass": "Tradeskill",
    "itemSubclass": "Cloth",
    "level": 10,
    "requiredLevel": 0,
    "sellPrice": 125,
    "description": "",
    "icon": "https://render.worldofwarcraft.com/us/icons/56/inv_fabric_silk_02.jpg",
    "wowhead": "https://www.wowhead.com/item=4291",
    "category": "tradegoods"
  },
  {
    "id": 4304,
    "name": "Thick Leather",
    "quality": "Common",
    "itemClass": "Tradeskill",
    "itemSubclass": "Leather",
    "level": 10,
    "requiredLevel": 0,
    "sellPrice": 300,
    "description": "",
    "icon": "https://render.worldofwarcraft.com/us/icons/56/inv_misc_leatherscrap_08.jpg",
    "wowhead": "https://www.wowhead.com/item=4304",
    "category": "tradegoods"
  },
  {
    "id": 4305,
    "name": "Bolt of Silk Cloth",
    "quality": "Common",
    "itemClass": "Tradeskill",
    "itemSubclass": "Cloth",
    "level": 10,
    "requiredLevel": 0,
    "sellPrice": 600,
    "description": "",
    "icon": "https://render.worldofwarcraft.com/us/icons/56/inv_fabric_silk_03.jpg",
    "wowhead": "https://www.wowhead.com/item=4305",
    "category": "tradegoods"
  },
  {
    "id": 4306,
    "name": "Silk Cloth",
    "quality": "Common",
    "itemClass": "Tradeskill",
    "itemSubclass": "Cloth",
    "level": 10,
    "requiredLevel": 0,
    "sellPrice": 150,
    "description": "",
    "icon": "https://render.worldofwarcraft.com/us/icons/56/inv_fabric_silk_01.jpg",
    "wowhead": "https://www.wowhead.com/item=4306",
    "category": "tradegoods"
  },
  {
    "id": 4337,
    "name": "Thick Spider's Silk",
    "quality": "Common",
    "itemClass": "Tradeskill",
    "itemSubclass": "Cloth",
    "level": 10,
    "requiredLevel": 0,
    "sellPrice": 750,
    "description": "",
    "icon": "https://render.worldofwarcraft.com/us/icons/56/spell_nature_web.jpg",
    "wowhead": "https://www.wowhead.com/item=4337",
    "category": "tradegoods"
  },
  {
    "id": 4338,
    "name": "Mageweave Cloth",
    "quality": "Common",
    "itemClass": "Tradeskill",
    "itemSubclass": "Cloth",
    "level": 10,
    "requiredLevel": 0,
    "sellPrice": 250,
    "description": "",
    "icon": "https://render.worldofwarcraft.com/us/icons/56/inv_fabric_mageweave_01.jpg",
    "wowhead": "https://www.wowhead.com/item=4338",
    "category": "tradegoods"
  },
  {
    "id": 4339,
    "name": "Bolt of Mageweave",
    "quality": "Common",
    "itemClass": "Tradeskill",
    "itemSubclass": "Cloth",
    "level": 10,
    "requiredLevel": 0,
    "sellPrice": 1250,
    "description": "",
    "icon": "https://render.worldofwarcraft.com/us/icons/56/inv_fabric_mageweave_03.jpg",
    "wowhead": "https://www.wowhead.com/item=4339",
    "category": "tradegoods"
  },
  {
    "id": 4340,
    "name": "Gray Dye",
    "quality": "Common",
    "itemClass": "Tradeskill",
    "itemSubclass": "Other",
    "level": 10,
    "requiredLevel": 0,
    "sellPrice": 87,
    "description": "",
    "icon": "https://render.worldofwarcraft.com/us/icons/56/inv_drink_10.jpg",
    "wowhead": "https://www.wowhead.com/item=4340",
    "category": "tradegoods"
  }
]